div-testbench/clock_divider.v
// Clock divider
module clock_divider #(

    // Parameters
    parameter               COUNT_WIDTH = 24,
    parameter [COUNT_WIDTH:0] MAX_COUNT = 6000000 - 1
)(
    
    // Inputs
    input   clk,
    input   rst,

    // Outputs
    output reg out
);

    // Internal signals
    reg div_clk;
    reg [COUNT_WIDTH:0] count;

    // Clock divider
    always @(posedge clk or posedge rst) begin
        if (rst == 1'b1) begin
            count <= 0;
            out <= 0;
        end else if (count == MAX_COUNT) begin
            count <= 0;
            out <= ~out;
        end else begin
            count <= count + 1'b1;
        end
    end

endmodule

div-testbench/clock_div_tb.v
// Defines timescale for simulation: <time_unit> / <time/precision>
`timescale 1ns/10ps

// Define ou-dividerr testbench
module clock_divider_tb ();

    // Internal signals
    wire    out;

    // Storage elements (set initial values to 0)
    reg     clk = 0;
    reg     rst = 0;

    // Simulation time: 10000 * 1 ns = 10 us
    localparam DURATION = 10000;

    // Generate clock signal: 1/ ((2 * 41.67) * 1 ns) = 11,999,040.08 MHz
    always begin
        
        //Delay for 41.67 time units
        // 10 ps precision means that 41.667 is rounded off to 41.67 ns.
        #41.667

        //Toggle clk line
        clk = ~clk;
    end

    //Instantiate unit under test (UUT)
    clock_divider #(.COUNT_WIDTH(4), .MAX_COUNT(6 - 1)) uut (
        .clk(clk), 
        .rst(rst),
        .out(out)
    );

    // Pulse reset line high at the beginning
    initial begin
        #10
        rst = 1'b1;
        #1
        rst = 1'b0;
    end

    // Run simulation (output to .vcd file)
    initial begin

        // Create simulation output file
        $dumpfile("clock_div_tb.vcd");
        $dumpvars(0, clock_divider_tb); // 0 means dump all variables data from all nested modules.

        // Wait for a given amount of time for simulation to complete
        #(DURATION)

        // Notify and end simulation
        $display("Finished!");
        $finish;
    end

endmodule

div-testbench/clock_div_tb.vcd
$date
	Sat Jul  2 16:18:19 2022
$end
$version
	Icarus Verilog
$end
$timescale
	1ps
$end
$scope module clock_divider_tb $end
$var wire 1 ! out $end
$var reg 1 " clk $end
$var reg 1 # rst $end
$scope module uut $end
$var wire 1 " clk $end
$var wire 1 # rst $end
$var reg 5 $ count [4:0] $end
$var reg 1 ! out $end
$upscope $end
$upscope $end
$enddefinitions $end
#0
$dumpvars
bx $
0#
0"
x!
$end
#10000
0!
b0 $
1#
#11000
0#
#41670
b1 $
1"
#83340
0"
#125010
b10 $
1"
#166680
0"
#208350
b11 $
1"
#250020
0"
#291690
b100 $
1"
#333360
0"
#375030
b101 $
1"
#416700
0"
#458370
1!
b0 $
1"
#500040
0"
#541710
b1 $
1"
#583380
0"
#625050
b10 $
1"
#666720
0"
#708390
b11 $
1"
#750060
0"
#791730
b100 $
1"
#833400
0"
#875070
b101 $
1"
#916740
0"
#958410
0!
b0 $
1"
#1000080
0"
#1041750
b1 $
1"
#1083420
0"
#1125090
b10 $
1"
#1166760
0"
#1208430
b11 $
1"
#1250100
0"
#1291770
b100 $
1"
#1333440
0"
#1375110
b101 $
1"
#1416780
0"
#1458450
1!
b0 $
1"
#1500120
0"
#1541790
b1 $
1"
#1583460
0"
#1625130
b10 $
1"
#1666800
0"
#1708470
b11 $
1"
#1750140
0"
#1791810
b100 $
1"
#1833480
0"
#1875150
b101 $
1"
#1916820
0"
#1958490
0!
b0 $
1"
#2000160
0"
#2041830
b1 $
1"
#2083500
0"
#2125170
b10 $
1"
#2166840
0"
#2208510
b11 $
1"
#2250180
0"
#2291850
b100 $
1"
#2333520
0"
#2375190
b101 $
1"
#2416860
0"
#2458530
1!
b0 $
1"
#2500200
0"
#2541870
b1 $
1"
#2583540
0"
#2625210
b10 $
1"
#2666880
0"
#2708550
b11 $
1"
#2750220
0"
#2791890
b100 $
1"
#2833560
0"
#2875230
b101 $
1"
#2916900
0"
#2958570
0!
b0 $
1"
#3000240
0"
#3041910
b1 $
1"
#3083580
0"
#3125250
b10 $
1"
#3166920
0"
#3208590
b11 $
1"
#3250260
0"
#3291930
b100 $
1"
#3333600
0"
#3375270
b101 $
1"
#3416940
0"
#3458610
1!
b0 $
1"
#3500280
0"
#3541950
b1 $
1"
#3583620
0"
#3625290
b10 $
1"
#3666960
0"
#3708630
b11 $
1"
#3750300
0"
#3791970
b100 $
1"
#3833640
0"
#3875310
b101 $
1"
#3916980
0"
#3958650
0!
b0 $
1"
#4000320
0"
#4041990
b1 $
1"
#4083660
0"
#4125330
b10 $
1"
#4167000
0"
#4208670
b11 $
1"
#4250340
0"
#4292010
b100 $
1"
#4333680
0"
#4375350
b101 $
1"
#4417020
0"
#4458690
1!
b0 $
1"
#4500360
0"
#4542030
b1 $
1"
#4583700
0"
#4625370
b10 $
1"
#4667040
0"
#4708710
b11 $
1"
#4750380
0"
#4792050
b100 $
1"
#4833720
0"
#4875390
b101 $
1"
#4917060
0"
#4958730
0!
b0 $
1"
#5000400
0"
#5042070
b1 $
1"
#5083740
0"
#5125410
b10 $
1"
#5167080
0"
#5208750
b11 $
1"
#5250420
0"
#5292090
b100 $
1"
#5333760
0"
#5375430
b101 $
1"
#5417100
0"
#5458770
1!
b0 $
1"
#5500440
0"
#5542110
b1 $
1"
#5583780
0"
#5625450
b10 $
1"
#5667120
0"
#5708790
b11 $
1"
#5750460
0"
#5792130
b100 $
1"
#5833800
0"
#5875470
b101 $
1"
#5917140
0"
#5958810
0!
b0 $
1"
#6000480
0"
#6042150
b1 $
1"
#6083820
0"
#6125490
b10 $
1"
#6167160
0"
#6208830
b11 $
1"
#6250500
0"
#6292170
b100 $
1"
#6333840
0"
#6375510
b101 $
1"
#6417180
0"
#6458850
1!
b0 $
1"
#6500520
0"
#6542190
b1 $
1"
#6583860
0"
#6625530
b10 $
1"
#6667200
0"
#6708870
b11 $
1"
#6750540
0"
#6792210
b100 $
1"
#6833880
0"
#6875550
b101 $
1"
#6917220
0"
#6958890
0!
b0 $
1"
#7000560
0"
#7042230
b1 $
1"
#7083900
0"
#7125570
b10 $
1"
#7167240
0"
#7208910
b11 $
1"
#7250580
0"
#7292250
b100 $
1"
#7333920
0"
#7375590
b101 $
1"
#7417260
0"
#7458930
1!
b0 $
1"
#7500600
0"
#7542270
b1 $
1"
#7583940
0"
#7625610
b10 $
1"
#7667280
0"
#7708950
b11 $
1"
#7750620
0"
#7792290
b100 $
1"
#7833960
0"
#7875630
b101 $
1"
#7917300
0"
#7958970
0!
b0 $
1"
#8000640
0"
#8042310
b1 $
1"
#8083980
0"
#8125650
b10 $
1"
#8167320
0"
#8208990
b11 $
1"
#8250660
0"
#8292330
b100 $
1"
#8334000
0"
#8375670
b101 $
1"
#8417340
0"
#8459010
1!
b0 $
1"
#8500680
0"
#8542350
b1 $
1"
#8584020
0"
#8625690
b10 $
1"
#8667360
0"
#8709030
b11 $
1"
#8750700
0"
#8792370
b100 $
1"
#8834040
0"
#8875710
b101 $
1"
#8917380
0"
#8959050
0!
b0 $
1"
#9000720
0"
#9042390
b1 $
1"
#9084060
0"
#9125730
b10 $
1"
#9167400
0"
#9209070
b11 $
1"
#9250740
0"
#9292410
b100 $
1"
#9334080
0"
#9375750
b101 $
1"
#9417420
0"
#9459090
1!
b0 $
1"
#9500760
0"
#9542430
b1 $
1"
#9584100
0"
#9625770
b10 $
1"
#9667440
0"
#9709110
b11 $
1"
#9750780
0"
#9792450
b100 $
1"
#9834120
0"
#9875790
b101 $
1"
#9917460
0"
#9959130
0!
b0 $
1"
