block_RAM/block_ram.v
// Inferred Block RAM
`default_nettype none
module block_RAM #(

    // Parameters
    parameter INIT_FILE = ""
)(
    
    // Inputs
    input               clk,
    input               w_en,
    input               r_en,
    input       [3:0]   w_addr,
    input       [3:0]   r_addr,
    input       [7:0]   w_data,

    // Output
    output  reg [7:0]   r_data
);

    // Declare memory
    reg [7:0]   mem [15:0];

    // Interface with the memory block
    always @(posedge clk) begin
        
        // write to memory
        if (w_en == 1'b1) begin
            mem[w_addr] <= w_data;
        end

        // Read from memory
        if (r_en == 1'b1) begin
            r_data <= mem[r_addr];
        end
    end

    // Initialization (if available)
    initial if (INIT_FILE) begin
        $readmemh (INIT_FILE, mem);
    end
    
endmodule

block_RAM/block_ram_tb.v
// Defines timescale for simulation
`timescale 1ns/10ps

// Define our testbench
module block_ram_tb();

    // Internal signals
    wire [7:0]  r_data;

    // Storage elements (set some initial values to 0)
    reg clk = 0;
    reg w_en = 0;
    reg r_en = 0;
    reg [3:0] w_addr;
    reg [3:0] r_addr;
    reg [7:0] w_data;
    integer i;

    // Simulation time: 10000 * 1 ns = 10 uS
    localparam DURATION = 10000;

    //Generate clk signal (~12 Mhz)
    always begin
        #41.67
        clk = ~clk;
    end

    // Instantiate UUT
    block_RAM #(.INIT_FILE("mem_init.txt")) uut (
        .clk(clk),
        .w_en(w_en),
        .r_en(r_en),
        .w_addr(w_addr),
        .r_addr(r_addr),
        .w_data(w_data),
        .r_data(r_data)
    );

    // Run test: write to location and read value back
    initial begin
        
        // Test 1: Read data
        for (i = 0; i < 16; i = i+1) begin
            #(2 * 41.67)
            r_addr = i;
            r_en = 1;
            #(2 * 41.67)
            r_addr = 0;
            r_en = 0;
        end

        // Test 2: Write to addr 0x0f and read it back
        #(2 * 41.67)
        w_addr = 'h0f;
        w_data = 'hA5;
        w_en = 1;
        #(2 * 41.67)
        w_addr = 0;
        w_data = 0;
        w_en = 0;
        r_addr = 'h0f;
        r_en = 1;
        #(2 * 41.67)
        r_addr = 0;
        r_en = 0;
    end

    // Run simulation
    initial begin
        
        // Create simlation output file
        $dumpfile("block_ram_tb.vcd");
        $dumpvars(0, block_ram_tb);

        // Wait for a given amount of time for simulation to complete
        #(DURATION)

        // Notify end of simulation
        $display ("Finished!");
        $finish;
    end
endmodule

block_RAM/block_ram_tb.vcd
$date
	Fri Jul 08 21:01:12 2022
$end
$version
	Icarus Verilog
$end
$timescale
	1ps
$end
$scope module block_ram_tb $end
$var wire 8 ! r_data [7:0] $end
$var reg 1 " clk $end
$var reg 4 # r_addr [3:0] $end
$var reg 1 $ r_en $end
$var reg 4 % w_addr [3:0] $end
$var reg 8 & w_data [7:0] $end
$var reg 1 ' w_en $end
$var integer 32 ( i [31:0] $end
$scope module uut $end
$var wire 1 " clk $end
$var wire 4 ) r_addr [3:0] $end
$var wire 1 $ r_en $end
$var wire 4 * w_addr [3:0] $end
$var wire 8 + w_data [7:0] $end
$var wire 1 ' w_en $end
$var reg 8 , r_data [7:0] $end
$upscope $end
$upscope $end
$enddefinitions $end
#0
$dumpvars
bx ,
bx +
bx *
bx )
b0 (
0'
bx &
bx %
0$
bx #
0"
bx !
$end
#41670
1"
#83340
0"
1$
b0 #
b0 )
#125010
b0 !
b0 ,
1"
#166680
0"
b1 (
0$
#208350
1"
#250020
0"
1$
b1 #
b1 )
#291690
b1 !
b1 ,
1"
#333360
0"
b10 (
0$
b0 #
b0 )
#375030
1"
#416700
0"
1$
b10 #
b10 )
#458370
b10 !
b10 ,
1"
#500040
0"
b11 (
0$
b0 #
b0 )
#541710
1"
#583380
0"
1$
b11 #
b11 )
#625050
b11 !
b11 ,
1"
#666720
0"
b100 (
0$
b0 #
b0 )
#708390
1"
#750060
0"
1$
b100 #
b100 )
#791730
b100 !
b100 ,
1"
#833400
0"
b101 (
0$
b0 #
b0 )
#875070
1"
#916740
0"
1$
b101 #
b101 )
#958410
b101 !
b101 ,
1"
#1000080
0"
b110 (
0$
b0 #
b0 )
#1041750
1"
#1083420
0"
1$
b110 #
b110 )
#1125090
b110 !
b110 ,
1"
#1166760
0"
b111 (
0$
b0 #
b0 )
#1208430
1"
#1250100
0"
1$
b111 #
b111 )
#1291770
b111 !
b111 ,
1"
#1333440
0"
b1000 (
0$
b0 #
b0 )
#1375110
1"
#1416780
0"
1$
b1000 #
b1000 )
#1458450
b10111000 !
b10111000 ,
1"
#1500120
0"
b1001 (
0$
b0 #
b0 )
#1541790
1"
#1583460
0"
1$
b1001 #
b1001 )
#1625130
b10111001 !
b10111001 ,
1"
#1666800
0"
b1010 (
0$
b0 #
b0 )
#1708470
1"
#1750140
0"
1$
b1010 #
b1010 )
#1791810
b10111010 !
b10111010 ,
1"
#1833480
0"
b1011 (
0$
b0 #
b0 )
#1875150
1"
#1916820
0"
1$
b1011 #
b1011 )
#1958490
b10111011 !
b10111011 ,
1"
#2000160
0"
b1100 (
0$
b0 #
b0 )
#2041830
1"
#2083500
0"
1$
b1100 #
b1100 )
#2125170
b10111100 !
b10111100 ,
1"
#2166840
0"
b1101 (
0$
b0 #
b0 )
#2208510
1"
#2250180
0"
1$
b1101 #
b1101 )
#2291850
b10111101 !
b10111101 ,
1"
#2333520
0"
b1110 (
0$
b0 #
b0 )
#2375190
1"
#2416860
0"
1$
b1110 #
b1110 )
#2458530
b10111110 !
b10111110 ,
1"
#2500200
0"
b1111 (
0$
b0 #
b0 )
#2541870
1"
#2583540
0"
1$
b1111 #
b1111 )
#2625210
b10111111 !
b10111111 ,
1"
#2666880
0"
b10000 (
0$
b0 #
b0 )
#2708550
1"
#2750220
0"
1'
b10100101 &
b10100101 +
b1111 %
b1111 *
#2791890
1"
#2833560
0"
1$
b1111 #
b1111 )
0'
b0 &
b0 +
b0 %
b0 *
#2875230
b10100101 !
b10100101 ,
1"
#2916900
0"
0$
b0 #
b0 )
